aby-0.2.0.dist-info/METADATA
aby-0.2.0.dist-info/WHEEL
aby/__init__.py
aby-0.2.0.dist-info/RECORD
